{"id":"6C7FA9FB-B903-4FD7-AB76-E907C1315B7B","validationEntity":{"analysedDataType":"auto","dataResult":{}},"modelEntity":{"createdDate":"2021-02-09T06:46:01Z","id":"EF455C7D-B73D-428B-8099-B706CA0D9EE3","experimentID":"6C7FA9FB-B903-4FD7-AB76-E907C1315B7B","title":"","modifiedDate":"2021-02-09T06:46:01Z","preferredFilename":"","version":"1.0","modelURL":"Models\/ImageClassificationDemo%201.mlmodel"},"version":"1.0","settingEntity":{"taskType":"imageClassifier","augmentations":[],"styleTransferAlgorithmType":"image","iterationCount":25,"transferLearningEmbeddingType":"dynamic","harVideoAugmentations":0,"algorithmType":"maxEnt","seedType":"default","featureNames":[]},"state":"trained","trainingEntity":{"finishTime":"2021-02-09T06:46:13Z","recipeTrainingResults":{"imageClassifier":{"confusionMatrix":[{"expected":"Cat","actual":"Cat","count":18},{"expected":"Dog","actual":"Dog","count":18},{"expected":"Other","actual":"Other","count":18}],"statsByLabel":{"Cat":{"count":18,"precisionRecall":{"success":{"recall":1,"precision":1}}},"Other":{"count":18,"precisionRecall":{"success":{"recall":1,"precision":1}}},"Dog":{"count":18,"precisionRecall":{"success":{"recall":1,"precision":1}}}},"accuracy":1}},"dataResult":{"itemsCount":63,"dataURL":"file:\/\/\/Users\/jaleel\/Developer\/iOS\/ImageClassificationDemo\/Training%20set\/Training\/","classesCount":3,"dataSourceID":"E92E4BE7-D452-469E-8FE5-DAE4E5734734","analysis":{"summary":{"sampleCount":63,"classCount":3,"canUseValidation":1},"issues":[{"description":"3 classes found, including Dog, Other, Cat","severity":"debug"},{"description":"63 images found, automatically creating validation set","severity":"good"},{"description":"Smallest class is \"Cat\" with 21 images","severity":"debug"},{"description":"Largest class is \"Dog\" with 21 images","severity":"debug"}],"classifierAnalysis":{"columns":[],"vizualizerSpec":"","labelStats":{"Cat":21,"Other":21,"Dog":21}}}},"dataURL":"file:\/\/\/Users\/jaleel\/Developer\/iOS\/ImageClassificationDemo\/Training%20set\/Training\/","featureExtractionCheckpointMayBeAvailable":false,"recipeValidationResults":{"imageClassifier":{"confusionMatrix":[{"expected":"Cat","actual":"Cat","count":3},{"expected":"Dog","actual":"Dog","count":3},{"expected":"Other","actual":"Other","count":3}],"statsByLabel":{"Cat":{"count":3,"precisionRecall":{"success":{"recall":1,"precision":1}}},"Other":{"count":3,"precisionRecall":{"success":{"recall":1,"precision":1}}},"Dog":{"count":3,"precisionRecall":{"success":{"recall":1,"precision":1}}}},"accuracy":1}},"progress":[{"currentRowIndex":0,"tableIndex":0,"count":0,"isLast":false,"percentComplete":0,"tableDone":false},{"icTrainingColumnHeader":{"hasValidation":true,"elapsedTime":0.014081,"trainingAccuracy":0.77777799999999997,"iterationCount":1,"validationAccuracy":0.66666700000000001},"isLast":false,"currentRowIndex":0,"count":1,"tableDone":false,"tableIndex":13,"percentComplete":0},{"icTrainingColumnHeader":{"hasValidation":true,"elapsedTime":0.031639,"trainingAccuracy":0.98148100000000005,"iterationCount":2,"validationAccuracy":1},"isLast":false,"currentRowIndex":0,"count":2,"tableDone":false,"tableIndex":13,"percentComplete":0},{"icTrainingColumnHeader":{"hasValidation":true,"elapsedTime":0.050789000000000001,"trainingAccuracy":0.98148100000000005,"iterationCount":3,"validationAccuracy":1},"isLast":false,"currentRowIndex":0,"count":3,"tableDone":false,"tableIndex":13,"percentComplete":0},{"icTrainingColumnHeader":{"hasValidation":true,"elapsedTime":0.072167999999999996,"trainingAccuracy":1,"iterationCount":4,"validationAccuracy":1},"isLast":false,"currentRowIndex":0,"count":4,"tableDone":false,"tableIndex":13,"percentComplete":0},{"icTrainingColumnHeader":{"hasValidation":true,"elapsedTime":0.100289,"trainingAccuracy":1,"iterationCount":5,"validationAccuracy":1},"isLast":false,"currentRowIndex":0,"count":5,"tableDone":false,"tableIndex":13,"percentComplete":0},{"icTrainingColumnHeader":{"hasValidation":true,"elapsedTime":0.187033,"trainingAccuracy":1,"iterationCount":10,"validationAccuracy":1},"isLast":false,"currentRowIndex":0,"count":10,"tableDone":true,"tableIndex":13,"percentComplete":0},{"currentRowIndex":0,"tableIndex":0,"count":15,"isLast":false,"percentComplete":0,"tableDone":false},{"currentRowIndex":0,"tableIndex":0,"count":20,"isLast":false,"percentComplete":0,"tableDone":false},{"currentRowIndex":0,"tableIndex":0,"count":25,"isLast":false,"percentComplete":0,"tableDone":false},{"currentRowIndex":0,"tableIndex":0,"count":30,"isLast":false,"percentComplete":0,"tableDone":false},{"currentRowIndex":0,"tableIndex":0,"count":35,"isLast":false,"percentComplete":0,"tableDone":false},{"currentRowIndex":0,"tableIndex":0,"count":40,"isLast":false,"percentComplete":0,"tableDone":false},{"currentRowIndex":0,"tableIndex":0,"count":45,"isLast":false,"percentComplete":0,"tableDone":false},{"currentRowIndex":0,"tableIndex":0,"count":50,"isLast":false,"percentComplete":0,"tableDone":false},{"currentRowIndex":0,"tableIndex":0,"count":55,"isLast":false,"percentComplete":0,"tableDone":false},{"currentRowIndex":0,"tableIndex":0,"count":60,"isLast":false,"percentComplete":0,"tableDone":false},{"currentRowIndex":0,"tableIndex":0,"count":63,"isLast":false,"percentComplete":0,"tableDone":true}],"trainingAccuracy":1,"checkpointMetrics":{},"analysedDataType":"datasource","dataSourceID":"E92E4BE7-D452-469E-8FE5-DAE4E5734734","snapshottableCheckpoints":{},"validationAccuracy":1,"startTime":"2021-02-09T06:46:12Z"},"createdDate":"2021-02-09T06:46:01Z","snapshotRole":{"withoutSnapshots":0},"evaluationEntities":[{"result":{"imageClassifier":{"statsByLabel":{"Cat":{"count":5,"precisionRecall":{"success":{"recall":1,"precision":1}}},"Other":{"count":5,"precisionRecall":{"success":{"recall":1,"precision":1}}},"Dog":{"count":5,"precisionRecall":{"success":{"recall":1,"precision":1}}}},"accuracy":1}},"dataURL":"file:\/\/\/Users\/jaleel\/Developer\/iOS\/ImageClassificationDemo\/Training%20set\/Testing\/","id":"e535202f-8b67-48ea-8d14-14a0281acfc5","dataResult":{"itemsCount":15,"dataURL":"file:\/\/\/Users\/jaleel\/Developer\/iOS\/ImageClassificationDemo\/Training%20set\/Testing\/","classesCount":3,"dataSourceID":"C2C78BAD-3393-426F-A02E-FD5C7B10F591","analysis":{"summary":{"sampleCount":15,"classCount":3,"canUseValidation":0},"issues":[{"description":"3 classes found, including Other, Cat, Dog","severity":"debug"},{"description":"Less than 50 total images found - add more to improve model validation","severity":"warning"},{"description":"Smallest class is \"Dog\" with 5 images","severity":"debug"},{"description":"Largest class is \"Other\" with 5 images","severity":"debug"}],"classifierAnalysis":{"columns":[],"vizualizerSpec":"","labelStats":{"Cat":5,"Other":5,"Dog":5}}}},"dataSourceID":"C2C78BAD-3393-426F-A02E-FD5C7B10F591","analysedDataType":"none","accuracy":1,"startTime":"2021-02-09T06:46:15Z","finishTime":"2021-02-09T06:46:15Z"},{"id":"81367655-490e-43de-ab16-7957bcd7f69b","dataResult":{"itemsCount":15,"dataURL":"file:\/\/\/Users\/jaleel\/Developer\/iOS\/ImageClassificationDemo\/Training%20set\/Testing\/","classesCount":3,"dataSourceID":"C2C78BAD-3393-426F-A02E-FD5C7B10F591","analysis":{"summary":{"sampleCount":15,"classCount":3,"canUseValidation":0},"issues":[{"description":"3 classes found, including Other, Cat, Dog","severity":"debug"},{"description":"Less than 50 total images found - add more to improve model validation","severity":"warning"},{"description":"Smallest class is \"Dog\" with 5 images","severity":"debug"},{"description":"Largest class is \"Other\" with 5 images","severity":"debug"}],"classifierAnalysis":{"columns":[],"vizualizerSpec":"","labelStats":{"Cat":5,"Other":5,"Dog":5}}}},"dataURL":"file:\/\/\/Users\/jaleel\/Developer\/iOS\/ImageClassificationDemo\/Training%20set\/Testing\/","dataSourceID":"C2C78BAD-3393-426F-A02E-FD5C7B10F591","analysedDataType":"none"}],"activityEntities":["evaluationStarted",[{"id":"F0F562DF-8EBC-4879-8D0E-17E61E2E3A48","title":"Testing Started","createdDate":"2021-02-09T06:46:15Z","event":"evaluationStarted","subtitle":"ImageClassificationDemo 1"}],"trainingFinished",[{"id":"3AF094A6-A6BF-415D-ABCE-8001EDE03DDB","title":"Training Completed","createdDate":"2021-02-09T06:46:13Z","event":"trainingFinished","subtitle":"Model converged at 10 iterations"}],"evaluationFinished",[{"id":"F177D148-82C7-4B2E-ACEA-EB0E4EFE96CD","title":"Testing Completed","createdDate":"2021-02-09T06:46:15Z","event":"evaluationFinished","subtitle":"ImageClassificationDemo 1"}],"trainingStarted",[{"id":"903FDBFC-0168-46B1-92ED-2C405B678A2B","title":"Training Started","createdDate":"2021-02-09T06:46:12Z","event":"trainingStarted","subtitle":"25 iterations"}],"experimentCreated",[{"id":"555E0822-66C7-4A62-8C75-3ED4EA422E06","title":"Model Source Created","createdDate":"2021-02-09T06:46:01Z","event":"experimentCreated","subtitle":"ImageClassificationDemo 1"}],"trainingDataAdded",[{"id":"4EF23972-F95B-48F7-8D2A-AA4338F4A822","title":"Training Data Added","createdDate":"2021-02-09T06:46:07Z","event":"trainingDataAdded","subtitle":"Training"}],"evaluationDataAdded",[{"id":"5A9D38E4-1CC6-49A3-A5D3-81072C6C3C5F","title":"Testing Data Added","createdDate":"2021-02-09T06:46:09Z","event":"evaluationDataAdded","subtitle":"Testing"}]],"title":"ImageClassificationDemo 1","evaluationEntity":{"result":{"imageClassifier":{"statsByLabel":{"Cat":{"count":5,"precisionRecall":{"success":{"recall":1,"precision":1}}},"Other":{"count":5,"precisionRecall":{"success":{"recall":1,"precision":1}}},"Dog":{"count":5,"precisionRecall":{"success":{"recall":1,"precision":1}}}},"accuracy":1}},"dataURL":"file:\/\/\/Users\/jaleel\/Developer\/iOS\/ImageClassificationDemo\/Training%20set\/Testing\/","id":"39fb20fa-635c-4435-8449-27ab3c47430a","dataResult":{"itemsCount":15,"dataURL":"file:\/\/\/Users\/jaleel\/Developer\/iOS\/ImageClassificationDemo\/Training%20set\/Testing\/","classesCount":3,"dataSourceID":"C2C78BAD-3393-426F-A02E-FD5C7B10F591","analysis":{"summary":{"sampleCount":15,"classCount":3,"canUseValidation":0},"issues":[{"description":"3 classes found, including Other, Cat, Dog","severity":"debug"},{"description":"Less than 50 total images found - add more to improve model validation","severity":"warning"},{"description":"Smallest class is \"Dog\" with 5 images","severity":"debug"},{"description":"Largest class is \"Other\" with 5 images","severity":"debug"}],"classifierAnalysis":{"columns":[],"vizualizerSpec":"","labelStats":{"Cat":5,"Other":5,"Dog":5}}}},"dataSourceID":"C2C78BAD-3393-426F-A02E-FD5C7B10F591","analysedDataType":"none","accuracy":1,"startTime":"2021-02-09T06:46:15Z","finishTime":"2021-02-09T06:46:15Z"},"evaluationState":"evaluated","contentDataResult":{},"modifiedDate":"2021-02-09T06:46:15Z","preferredFilename":"ImageClassificationDemo 1"}